{
  "id": "046",
  "created_at": "2026-07-22T13:38:57+00:00",
  "updated_at": "2026-07-23T13:58:56+00:00",
  "status": "published",
  "category": "deep_sea",
  "series": "심해 도감",
  "species": {
    "common_name_ko": "민태과",
    "common_name_en": "Macrouridae",
    "scientific_name": "Macrouridae",
    "depth_range_m": "100-6000",
    "habitat": "",
    "distribution": "",
    "diet": [],
    "fun_facts": [
      "ソコダラ科（学名:Macrouridae）は、タラ目ソコダラ亜目に所属する魚類の分類群の一つ。タラ目で最大のグループである。学名の由来は、ギリシャ語の「makros（大きな）」+「oura（尾）」から。"
    ]
  },
  "reels": {
    "hook": "深海、異形。巨大な尾、潜む。",
    "caption": "深く沈んだ海の底、光もほとんど届かない領域に、ひとつの影が静かに漂っています。\n姿を捉えようとしても、輪郭はすぐに闇へ溶けていき、そこにいたことすら疑いたくなる——そんな生き物が、深海の底に暮らしているといいます。\nその名はソコダラ(学名: Macrouridae)。\n棲み処は、水深わずか100メートルほどの浅場から、6000メートルという想像を絶する深みまで及ぶそうです。浅い持ち場もあれば、光の届かぬ最深の持ち場もある。配属先は選べませんし、異動願いも受け付けていないようです。\nソコダラ科は、タラ目ソコダラ亜目というグループの中で、最大の一族を形成しているといいます。深海という限られた世界の中で、これほど大きな所帯を築き上げてきたことは、それだけで驚くべきことです。深海というフロアの中で、いちばん人数の多い部署——それがソコダラという集団なのかもしれません。\nその学名Macrouridaeは、ギリシャ語で「大きな」を意味する「makros」と、「尾」を意味する「oura」を組み合わせて名付けられたそうです。長く伸びるその尾こそが、この魚たちを象徴する姿。名は体を表す、とはまさにこのことなのでしょう。\nもしこの物語が心に触れたなら、どうか保存しておいてください。\nそして、同じ海を想う誰かにも、そっとシェアしてあげてください。\n映像: NOAA Ocean Exploration・Public Domain\n写真: null · CC BY",
    "hashtags": [
      "#ソコダラ",
      "#深海生物"
    ],
    "reveal_name": "ソコダラ / Macrouridae",
    "reveal_fact": "深海・巨大・長い尾、タラ目最大",
    "hook_ko": "심해의 거대, 꼬리만 길게 뻗어.",
    "caption_ko": "깊이 가라앉은 바다 밑바닥, 빛조차 거의 닿지 않는 영역에서 그림자 하나가 조용히 떠돌고 있습니다.\n그 모습을 눈으로 좇으려 해도 윤곽은 이내 어둠 속으로 녹아들어, 정말 그곳에 있었는지조차 의심하게 되는——그런 생물이 심해 바닥에 살고 있다고 합니다.\n그 이름은 민태과(학명: Macrouridae)입니다.\n서식지는 수심 겨우 100미터 정도의 얕은 곳부터, 6000미터라는 상상을 초월하는 깊은 곳까지 이른다고 합니다. 얕은 근무지도 있고, 빛이 닿지 않는 가장 깊은 근무지도 있습니다. 배치는 선택할 수 없습니다, 전근 신청도 받아주지 않는 모양입니다.\n민태과는 대구목 민태아목이라는 그룹 안에서 가장 큰 일족을 이루고 있다고 합니다. 심해라는 제한된 세계 속에서 이만큼 큰 식구를 이루어왔다는 것, 그 자체만으로도 놀라운 일입니다. 심해라는 층에서 가장 인원이 많은 부서——그것이 바로 민태과라는 집단일지도 모릅니다.\n학명 Macrouridae는 그리스어로 '크다'를 뜻하는 'makros'와 '꼬리'를 뜻하는 'oura'를 합쳐 붙여졌다고 합니다. 길게 뻗은 그 꼬리야말로 이 물고기들을 상징하는 모습입니다. 이름이 곧 그 존재를 말해준다는 것은, 바로 이런 경우를 두고 하는 말인가 봅니다.\n만약 이 이야기가 마음에 와닿았다면, 부디 저장해두시길 바랍니다.\n그리고 같은 바다를 생각하는 누군가에게도, 살며시 공유해주세요.\n영상: NOAA Ocean Exploration・Public Domain",
    "hashtags_ko": [
      "#민태과",
      "#심해생물"
    ],
    "yt_title": "配属先は選べない深海魚ソコダラ #ソコダラ #深海生物",
    "yt_title_ko": "배치는 선택 불가 심해어 민태과 #민태과 #심해생물",
    "visualizer": "reels",
    "video_file": "macrouridae_20260723_135855.mp4"
  },
  "source": {
    "image_credit": "",
    "info_sources": [
      "Wikipedia (ja)",
      "Wikimedia Commons (File:Grenadier (Macrouridae) par 400 m de fond (Ifremer 00621-73302).jpg)"
    ],
    "license": ""
  },
  "media": {
    "video_url": "https://github.com/jtaechul/Product/releases/download/content-046/reels_046.mp4",
    "rev": "30013009987",
    "cover_url": "https://github.com/jtaechul/Product/releases/download/content-046/cover_046.jpg",
    "yt_thumb_url": "https://github.com/jtaechul/Product/releases/download/content-046/ytthumb_046.jpg"
  },
  "post": null
}